livingdocs/__init__.py
livingdocs/__main__.py
livingdocs/cli.py
livingdocs/hugo_doc.py
livingdocs/maker.py
livingdocs/static_site.py
livingdocs/site_files/layouts/index.html
livingdocs/site_files/layouts/_default/list.html
livingdocs/site_files/layouts/_default/single.html
livingdocs/site_files/layouts/partials/footer.html
livingdocs/site_files/layouts/partials/header.html
livingdocs/site_files/layouts/partials/sidebar-single.html
livingdocs/site_files/layouts/section/feature.html
livingdocs/site_files/layouts/section/term.html
livingdocs/site_files/layouts/term/single.html
livingdocs/site_files/static/css/bootstrap.min.css
livingdocs/site_files/static/fonts/glyphicons-halflings-regular.eot
livingdocs/site_files/static/fonts/glyphicons-halflings-regular.svg
livingdocs/site_files/static/fonts/glyphicons-halflings-regular.ttf
livingdocs/site_files/static/fonts/glyphicons-halflings-regular.woff
livingdocs/site_files/static/fonts/glyphicons-halflings-regular.woff2
livingdocs/site_files/static/js/angular-animate.min.js
livingdocs/site_files/static/js/angular.min.js
livingdocs/site_files/static/js/ui-bootstrap-tpls-1.2.1.min.js
livingdocs-0.2.0.dist-info/DESCRIPTION.rst
livingdocs-0.2.0.dist-info/METADATA
livingdocs-0.2.0.dist-info/RECORD
livingdocs-0.2.0.dist-info/WHEEL
livingdocs-0.2.0.dist-info/entry_points.txt
livingdocs-0.2.0.dist-info/metadata.json
livingdocs-0.2.0.dist-info/top_level.txt
