Metadata-Version: 2.0
Name: livingdocs
Version: 0.2.0
Summary: Create living documentation from BDD specs
Home-page: https://github.com/discogs/python-livingdocs
Author: Andy Craze
Author-email: acraze@discogsinc.com
License: BSD
Keywords: bdd,documentation,tools
Platform: UNKNOWN
Classifier: Development Status :: 5 - Production/Stable
Classifier: Intended Audience :: Developers
Classifier: License :: OSI Approved :: BSD License
Classifier: Operating System :: Unix
Classifier: Operating System :: POSIX
Classifier: Operating System :: Microsoft :: Windows
Classifier: Programming Language :: Python
Classifier: Programming Language :: Python :: 2.7
Classifier: Programming Language :: Python :: 3
Classifier: Programming Language :: Python :: 3.3
Classifier: Programming Language :: Python :: 3.4
Classifier: Programming Language :: Python :: 3.5
Classifier: Topic :: Utilities
Requires-Dist: awesome-slugify
Requires-Dist: click
